{"help":"https://data.gov.hk/tc-data/api/3/action/help_show?name=package_show","success":true,"result":{"license_title":null,"maintainer":"詢問處","relationships_as_object":[],"private":false,"maintainer_email":"enquiry@dsd.gov.hk","num_tags":0,"update_frequency":"每年","id":"d562946d-8136-4b95-99d5-cbb66bfbdcce","metadata_created":"2019-06-27T00:45:48.058205","metadata_modified":"2019-06-27T00:45:51.474393","author":null,"author_email":null,"state":"active","version":null,"license_id":null,"type":"dataset","resources":[{"shared_id":"e7ec6898987411e9b855005056896ca6","inLanguage":"en","cache_last_updated":null,"datePublished":"2019-06-27","package_id":"d562946d-8136-4b95-99d5-cbb66bfbdcce","id":"5b8857a0-88e6-4fde-adef-e4ccb1d52b71","size":null,"state":"active","hash":"","description":"有關整體污水處理工作的資料。","format":"CSV","dateCreated":"2019-06-01","mimetype_inner":null,"url_type":null,"mimetype":null,"cache_url":null,"name":"便覽(污水處理) (英文)","created":"2019-06-27T00:45:49.107645","url":"http://www.dsd.gov.hk/datagovhk/data/sewage_treatment_eng.csv","is_api":"N","last_modified":null,"position":0,"revision_id":"121bdbc9-6f48-48bf-9988-1ba7eb429c0e","resource_type":null},{"shared_id":"e89f3432987411e9b855005056896ca6","inLanguage":"zh-Hant","cache_last_updated":null,"datePublished":"2019-06-27","package_id":"d562946d-8136-4b95-99d5-cbb66bfbdcce","id":"60ce6436-ef90-4ac7-934b-12f8daae731b","size":null,"state":"active","hash":"","description":"有關整體污水處理工作的資料。","format":"CSV","dateCreated":"2019-06-01","mimetype_inner":null,"url_type":null,"mimetype":null,"cache_url":null,"name":"便覽(污水處理) (繁體中文)","created":"2019-06-27T00:45:50.303508","url":"http://www.dsd.gov.hk/datagovhk/data/sewage_treatment_tch.csv","is_api":"N","last_modified":null,"position":1,"revision_id":"389f0dcb-62c4-49b8-aedc-d671c94ab768","resource_type":null},{"shared_id":"e95af564987411e9b855005056896ca6","inLanguage":"zh-Hans","cache_last_updated":null,"datePublished":"2019-06-27","package_id":"d562946d-8136-4b95-99d5-cbb66bfbdcce","id":"09b0673a-53d9-4819-9e06-7b40ed9fd1e2","size":null,"state":"active","hash":"","description":"有關整體污水處理工作的資料。","format":"CSV","dateCreated":"2019-06-01","mimetype_inner":null,"url_type":null,"mimetype":null,"cache_url":null,"name":"便覽(污水處理) (簡體中文)","created":"2019-06-27T00:45:51.523799","url":"http://www.dsd.gov.hk/datagovhk/data/sewage_treatment_sch.csv","is_api":"N","last_modified":null,"position":2,"revision_id":"7e03e953-aa71-43da-b81f-b53ef13ca0f3","resource_type":null}],"maintainer_phone":"25947080","num_resources":3,"tags":[],"groups":[{"display_name":"環境","description":"","image_display_url":"","title":"環境","id":"a399f260-bfa3-4105-95e3-30bd9c47238c","name":"environment"}],"creator_user_id":"3a38bc6f-6115-4085-9ab4-533d28c95175","relationships_as_subject":[],"organization":{"description":"","created":"2019-02-01T18:22:37.304844","title":"渠務署","name":"hk-dsd","is_organization":true,"state":"active","image_url":"https://data.gov.hk/filestore/provider-images/hk-dsd.png","revision_id":"d296cb01-1500-4492-a6a1-2137ab6fcb3a","type":"organization","id":"f4aa205b-9e4b-4644-b7d2-5948db23493b","approval_status":"approved"},"name":"hk-dsd-dsd_psi_1-fs-sewage-treatment","isopen":false,"data_dictionary":"http://www.dsd.gov.hk/datagovhk/data_dict/Data_Dictionary_of_Factsheet_tch.pdf","notes":"有關整體污水處理工作的資料。","owner_org":"f4aa205b-9e4b-4644-b7d2-5948db23493b","url":null,"title":"便覽(污水處理)","revision_id":"cd87aab7-65eb-4ebf-84eb-cd1fcf6ee0f4"}}