{"help":"https://data.gov.hk/tc-data/api/3/action/help_show?name=package_show","success":true,"result":{"license_title":null,"maintainer":"高級牙科醫生 (行政)","relationships_as_object":[],"private":false,"maintainer_email":"sdo_admin@dh.gov.hk","num_tags":0,"update_frequency":"每年","id":"c0a439e2-4571-4172-9084-9dd8fc430b99","metadata_created":"2019-02-19T18:05:46.576081","metadata_modified":"2019-03-23T09:14:07.070119","author":null,"author_email":null,"state":"active","version":null,"license_id":null,"type":"dataset","resources":[{"shared_id":"00f5bc8c4d4c11e9ac49005056896ca6","cache_url":null,"hash":"","description":"二零一三年至二零一七年口腔健康教育組的工作","name":"口腔健康教育組的工作 (英文)","cache_last_updated":null,"url":"http://www.dh.gov.hk/datagovhk/ncdd/Work%20of%20Oral%20Health%20Education%20Unit%20(English).csv","format":"CSV","is_api":"N","state":"active","created":"2019-03-23T09:14:04.604380","package_id":"c0a439e2-4571-4172-9084-9dd8fc430b99","mimetype_inner":null,"mimetype":null,"last_modified":null,"position":0,"revision_id":"b21fdc58-c8be-4744-9186-211e975480ce","url_type":null,"id":"3378ad89-0d81-4896-b605-2325aeaf0dae","resource_type":null,"size":null},{"shared_id":"01ba82c44d4c11e9ac49005056896ca6","cache_url":null,"hash":"","description":"二零一三年至二零一七年口腔健康教育組的工作","name":"口腔健康教育組的工作 (繁體中文)","cache_last_updated":null,"url":"http://www.dh.gov.hk/datagovhk/ncdd/Work%20of%20Oral%20Health%20Education%20Unit%20(Traditional%20Chinese).csv","format":"CSV","is_api":"N","state":"active","created":"2019-03-23T09:14:05.866755","package_id":"c0a439e2-4571-4172-9084-9dd8fc430b99","mimetype_inner":null,"mimetype":null,"last_modified":null,"position":1,"revision_id":"e93bbf71-e3f5-4414-97a4-1b4223b7f6a8","url_type":null,"id":"7f3398e5-dec1-475a-9398-92e1e367f81b","resource_type":null,"size":null},{"shared_id":"027819c44d4c11e9ac49005056896ca6","cache_url":null,"hash":"","description":"二零一三年至二零一七年口腔健康教育組的工作","name":"口腔健康教育組的工作 (簡體中文)","cache_last_updated":null,"url":"http://www.dh.gov.hk/datagovhk/ncdd/Work%20of%20Oral%20Health%20Education%20Unit%20(Simplified%20Chinese).csv","format":"CSV","is_api":"N","state":"active","created":"2019-03-23T09:14:07.114950","package_id":"c0a439e2-4571-4172-9084-9dd8fc430b99","mimetype_inner":null,"mimetype":null,"last_modified":null,"position":2,"revision_id":"f9098d14-e46f-4b4e-8355-a973bb994325","url_type":null,"id":"4d86f652-62bc-431c-a191-b0982ba70a83","resource_type":null,"size":null}],"maintainer_phone":"2961 8970","num_resources":3,"tags":[],"groups":[{"display_name":"衞生","description":"","image_display_url":"","title":"衞生","id":"aaeb1eac-a6d0-404b-b007-c3106b37a898","name":"health"}],"creator_user_id":"3a38bc6f-6115-4085-9ab4-533d28c95175","relationships_as_subject":[],"organization":{"description":"","created":"2019-02-01T18:22:36.209071","title":"衞生署","name":"hk-dh","is_organization":true,"state":"active","image_url":"https://data.gov.hk/filestore/provider-images/hk-dh.png","revision_id":"456409f2-e18c-4984-99fe-31b974f0dcb5","type":"organization","id":"3e8d5c2e-02a5-4dd9-aeb8-c70a46275f6e","approval_status":"approved"},"name":"hk-dh-dh_ncddhss-dh-ds-oral","isopen":false,"url":null,"notes":"二零一三年至二零一七年口腔健康教育組的工作","owner_org":"3e8d5c2e-02a5-4dd9-aeb8-c70a46275f6e","title":"口腔健康教育組的工作","revision_id":"97a83d9b-e269-45a5-a3bd-e9c442e2438d"}}